git_ling/__init__.py
git_ling/cli.py
git_ling/git_ling.py
git_ling/language_fetcher.py
git_ling/schemas.py
pylinguist/__init__.py
pylinguist/language_fetcher.py
pylinguist/pylinguist.py
pylinguist/schemas.py
tests/__init__.py
tests/test_cli.py
tests/test_git_ling.py
tests/test_language_fetcher.py
tests/test_pylinguist.py
git_ling-0.3.3.dist-info/LICENSE
git_ling-0.3.3.dist-info/METADATA
git_ling-0.3.3.dist-info/WHEEL
git_ling-0.3.3.dist-info/entry_points.txt
git_ling-0.3.3.dist-info/top_level.txt
git_ling-0.3.3.dist-info/RECORD
