Metadata-Version: 2.1
Name: git-ling
Version: 0.3.3
Summary: git_ling is a small library to detect programming languages from file names and extensions
Home-page: UNKNOWN
Author: Daniel Piro
License: UNKNOWN
Platform: UNKNOWN
Classifier: License :: OSI Approved :: MIT License
Classifier: Programming Language :: Python :: 3.6
Classifier: Development Status :: 3 - Alpha
Classifier: Intended Audience :: Developers
Classifier: Topic :: Software Development :: Libraries :: Python Modules
Requires-Dist: pydantic
Requires-Dist: pyyaml
Requires-Dist: requests
